{
  "job_id": "indeed-ma-2026-039",
  "source": "indeed-ma",
  "source_url": "https://ma.indeed.com/viewjob?jk=5a6675c56b0f6a54",
  "source_ref": "5a6675c56b0f6a54",
  "title": "AI Engineer / Data Scientist Expérimenté F/H",
  "title_normalized": "ML_ENGINEER",
  "company": "Deloitte",
  "company_type": "entité morale privée",
  "location": "Maroc",
  "country": "MA",
  "remote_policy": "on-site",
  "posted_date": "2026-05-14",
  "deadline_date": null,
  "contract_type": "CDI",
  "experience_min_years": null,
  "experience_max_years": null,
  "salary_range": null,
  "description": "Titre: AI Engineer / Data Scientist Expérimenté F/H\nEntreprise: Deloitte (Deloitte Extended Services · 3.9/5 étoiles · filiale 100% Deloitte France · basée Casablanca)\nLieu: Maroc (Casablanca)\nContrat: CDI\nURL: https://ma.indeed.com/viewjob?jk=5a6675c56b0f6a54\n\nMission:\nÉquipe Engineering, AI & Data — Consultant expérimenté Data Scientist/AI Engineering — accompagner clients dans projets de transformation data et IA.\n\nResponsabilités:\n- Compréhension approfondie des statistiques\n- Capacité à explorer, nettoyer et transformer les données\n- Construction et évaluation de modèles prédictifs\n- Solides bases en algorithmes pour l'optimisation des modèles\n- Expérience avec frameworks de deep learning : TensorFlow, PyTorch, ou Keras\n- Expérience avec techniques de NLP & Computer Vision\n- Familiarité avec services Cloud (AWS, GCP, Azure)\n- Expérience avec containers et déploiement : Docker, Kubernetes\n- Capacité à expliquer concepts complexes à parties prenantes non techniques\n- Compréhension des implications éthiques du développement AI\n- Protocole de sécurité des données et algorithmes\n- Bibliothèques de visualisation : Matplotlib, Seaborn, Plotly\n- Présentation résultats de manière claire et compréhensible\n\nProfil recherché:\n- Bac+5 école d'ingénieurs ou commerce avec spécialisation data\n",
  "skills_required": [
    "Deep Learning",
    "NLP",
    "Computer Vision",
    "TensorFlow",
    "PyTorch",
    "Keras",
    "Azure",
    "AWS",
    "GCP",
    "Docker",
    "Kubernetes",
    "Statistics",
    "Matplotlib",
    "Seaborn",
    "Plotly"
  ],
  "skills_optional": [],
  "responsibilities": [],
  "tools_mentioned": [
    "Azure",
    "AWS",
    "GCP",
    "Docker",
    "Kubernetes",
    "Matplotlib",
    "Seaborn",
    "Plotly"
  ],
  "frameworks_mentioned": [
    "TensorFlow",
    "PyTorch",
    "Keras"
  ],
  "languages_programming": [],
  "domains_iaml": [],
  "job_family": "ML_ENGINEER",
  "scraped_at": "2026-05-14T21:30:00Z",
  "scraper": "skillnav-playwright-mcp-v1.0",
  "rgpd_compliant": true,
  "personal_data_stripped": true,
  "extraction_confidence": 0.92,
  "extraction_method": "playwright + detail extraction",
  "query_used": "machine learning"
}