{
  "job_id": "indeed-ma-2024-057",
  "source": "indeed-ma",
  "source_url": "https://ma.indeed.com/viewjob?jk=f052434b162d925d",
  "source_url_wayback": "https://web.archive.org/web/20240101000000*/ma.indeed.com/viewjob?jk=f052434b162d925d",
  "source_ref": "f052434b162d925d",
  "title": "Data Analyst (REF05)",
  "title_normalized": "DATA_ANALYST",
  "company": "Trusted Advisors",
  "company_type": "entité morale privée",
  "location": "Ain-Sebaa 20250",
  "country": "MA",
  "remote_policy": "unknown",
  "posted_date": "2026-02-26T21:33:59.104Z",
  "first_seen_in_wayback": "2024-01-01",
  "last_seen_in_wayback": "2025-06-01",
  "wayback_snapshots_count": 32,
  "deadline_date": null,
  "contract_type": null,
  "experience_min_years": null,
  "experience_max_years": null,
  "salary_range": null,
  "description": "Nous recherchons pour le compte d'une banque de la place à Casablanca, un Data Analyst.\n\nPrincipales Missions:\n\nProduire des Dashboards pour le métier en se basant sur les besoins définis.\nAdapter les applicatifs aux besoins des métiers de la banque.\nPiloter les développements nécessaires autour des Dashboard.\nFournir toute aide nécessaire pour la mise en place des Dashboard pour le métier.\nMener des formations pour les nouvelles entrantes ainsi que les nouveaux utilisateurs et produire la documentation nécessaire.\n\nExpertise souhaitable :\n\nProfil Sénior en Gestion de Projet (réalisation du planning du projet, gestion des priorités, pilotage et coordination des tâches et des intervenants du projet, formalisation des documents, conduite des tests, compte-rendu, présentations, ...) avec une connaissance des process et activités de la banque.\nMaîtrise Tableau pour développement.\nExpert en Data science, Data Analysis, Data modélisation et visualisation.\nExpertise Tableau nécessaire et Alteryx souhaitée.\nConnaissance en méthodologie Agile.\n\nType de Contrat: Freelance\n\nDurée de la mission: 3 mois renouvelables\n\nLieu: Casablanca",
  "skills_required": [],
  "skills_optional": [],
  "responsibilities": [],
  "tools_mentioned": [],
  "frameworks_mentioned": [],
  "languages_programming": [],
  "domains_iaml": [],
  "job_family": "DATA_ANALYST",
  "scraped_at": "2026-05-14T21:35:00Z",
  "scraper": "skillnav-apify-indeed-recovery-v1.0",
  "rgpd_compliant": true,
  "personal_data_stripped": true,
  "extraction_confidence": 0.92,
  "extraction_method": "wayback_machine_listing_snapshot",
  "extraction_note": "Fiche historique reconstituée depuis snapshot Wayback du 2024-01-01 (32 snapshots Wayback contiennent ce jk). Détail complet inaccessible (Wayback ne snapshote pas les viewjob individuels).",
  "recovery_via": "apify_misceres_indeed_scraper"
}