{
  "job_id": "intl-ai-corpus-0067",
  "source": "intl-ai-corpus",
  "source_ref": "6837630",
  "source_url": "https://builtin.com/job/distinguished-engineer-data-ml-ai-office-cto/6837630",
  "title": "Distinguished Engineer, Data, ML & AI, Office of the CTO",
  "title_normalized": "AI_ENGINEER",
  "company": "Equinix",
  "company_type": "entité morale privée",
  "location": "US",
  "city_inferred": null,
  "country": "US",
  "remote_policy": "unknown",
  "posted_date": "2026-01-22",
  "publication_month": "2026-01",
  "contract_type": "CDI",
  "work_type_raw": "FULL_TIME",
  "experience_level_text": "Expert/Leader",
  "experience_min_years": null,
  "experience_max_years": null,
  "salary_range": null,
  "company_size_raw": "10,765 Employees",
  "company_stage": "Public",
  "company_focus": "Global digital infrastructure and connectivity platform",
  "industries": [
    "Big Data",
    "Cloud",
    "Internet of Things"
  ],
  "description": "Who are we?\n\nEquinix is the world’s digital infrastructure company®,\nshortening the path to connectivity to enable the\ninnovations that enrich our work, life and planet.\n\nA place where tech thinkers and future builders turn bold\nideas into breakthrough experiences, we welcome your unique\nperspective.Help us challenge assumptions, uncover bias, and\nremove barriers—because progress starts with fresh ideas.\nYou’ll find belonging, purpose, and a team that welcomes\nyou—because when you feel valued, you’re empowered to do\nyour best work.\n\nJob Summary\n\nThe Office of the CTO (OCTO) at Equinix is chartered with\ndriving the technology vision, strategy, and architecture to\nsupport the company’s overall business objectives. The OCTO\nteam also leads the technical innovation function with a\nstrong focus on software transformation and fostering\nengagements within software ecosystems and developer\ncommunities. The OCTO team is seeking a Distinguished\nEngineer, Data, ML & AI, Technology and Architecture to join\nour team of seasoned technologists. The ideal candidate will\npossess a strong passion for data life cycle management and\na diverse technological background in areas pertinent to\ndata and infrastructure, including distributed systems,\ncloud-native computing, machine learning, and artificial\nintelligence. As a Distinguished Engineer, you will have the\nopportunity to lead next-generation technology initiatives,\nhelp drive the technology vision and target architectures of\nEquinix's technology stacks and serve as a mentor and\nthought leader within the technical community at Equinix and\nbeyond. This is a senior position and an excellent\nopportunity for an experienced technical leader to join our\nteam and make a significant, sustainable impact on our\ntechnology stacks. If you fully believe in the power of\ntechnology to change the world, we would like to talk to\nyou.\n\nResponsibilities\n\n- Provide in-depth technical expertise to manage end-to-end\n  data lifecycle and deliver reliable and timely data at\n  Equinix, by identifying, evaluating and developing next-\n  generation technologies and architecture for the\n  infrastructure and services required\n- Deliver deep and broad architecture expertise across various\n  areas including data engineering (data lakes/stores, data\n  processing engines, search, data infrastructure);\n  analytics and ML (data pipeline as a service, query\n  engines, compute frameworks, MLOps, model building,\n  feature engineering, etc.); and data governance as a\n  service (data models, catalogs, discovery, data lineage,\n  audit, security, master data management, etc.)\n- Drive proof-of-concept technology development initiatives,\n  in close partnership with stakeholders, to deliver\n  tangible outcomes that will help guide new technology\n  investments and design decisions for data life cycle\n  management at Equinix\n- Serve as a visible technology thought leader in the industry\n  through various engagements focused on articulating\n  Equinix’s technology vision, strategy and architecture\n\nQualifications\n\n- Preferably, a Ph.D. or master’s degree in computer science,\n  or relevant engineering field\n- Proven years of experience, including 12+ years of relevant\n  technology, architecture or engineering leadership\n  experience\n- Demonstrable leadership, visionary accomplishments, and\n  extensive experience in developing data-related\n  technologies and architectures implemented in large-\n  scale/mission-critical deployments. Examples include solid\n  background in data infrastructure architecture,\n  engineering, DevOps, security, tooling, products, etc.\n- Solid understanding of data-as-a-service architectures\n- Excellent writing and verbal communications skills from\n  engineering to executive\n- Excellent collaboration and people skills\n\nThis posting is a new position within our organization.\n\nThe targeted pay range for this position in the following\nlocation is / locations are:\n\nCanada - Toronto Office TRO : 222,000 - 334,000 CAD / Annual\n\nUnited States - Dallas Infomart Office DAI : 230,000 -\n346,000 USD / Annual\n\nUnited States - Redwood City Office GHQ : 250,000 - 374,000\nUSD / Annual\n\nOur pay ranges reflect the minimum and maximum target for\nnew hire pay for the full-time position determined by role,\nlevel, and location.The pay range shown is based on our\ncompensation structure in place at the time of posting and\nmay be updated periodically based on business needs.\nIndividual pay is based on additional factors including job-\nrelated skills, experience, and relevant education and/or\ntraining.\n\nThe targeted pay range listed reflects the base pay only and\ndoes not include bonus, equity, or benefits. Employees are\neligible for bonus, and equity may be offered depending on\nthe position.\n\nEquinix Benefits\n\nAs an employee, you become important to Equinix’s success.\nWe ensure all your benefits are in line with our core\nvalues: competitive, inclusive, sustainable, connected and\nefficient. We keep them competitive within the current\nmarketplace to ensure we’re providing you with the best\npackage possible. So, wherever you are in your career and\nlife, you’ll be able to enhance your experience and bring\nyour whole self to work.\n\nEmployee Assistance Program: An Employee Assistance program\nis available to all employees.\n\nUS Benefits: - Insurance: You may enroll in health, life,\ndisability and voluntary plans that are designed for you and\nyour eligible family members. - Retirement: You and Equinix\nmay contribute to a retirement plan to help you plan for\nyour financial future. - Paid Time Off (PTO) and Paid\nHolidays: You will receive an accrued amount of PTO each pay\nperiod along with various paid holidays for you to rest and\nrecharge. Eligibility requirements apply to some benefits.\nBenefits are subject to change and may be subject to\nspecific plan or program terms.\n\nCanada Core Benefits: - Insurance: You may enroll in\nhealthcare coverage that is designed to complement the\nprovincial healthcare system, along with life, disability\nand optional benefit plans that are designed for you and\nyour eligible family members. - Retirement: You may also\nenroll in Equinix-sponsored retirement or savings plans:\nDefined Contribution Pension Plan (DCPP), Group Retirement\nSavings Plan (RRSP) and Tax-Free Savings Plan (TSFA). -\nVacation and Paid Holidays: Equinix offers both vacation and\npersonal time, along with various paid holidays for you to\nrest and recharge. Eligibility requirements apply to some\nbenefits. Benefits are subject to specific plan or program\nterms, and to change at Equinix discretion.\n\nEquinix is committed to ensuring that our employment process\nis open to all individuals, including those with a\ndisability.  If you are a qualified candidate and need\nassistance or an accommodation, please let us know by\ncompleting this form.\n\nEquinix is an Equal Employment Opportunity and, in the U.S.,\nan Affirmative Action employer.  All qualified applicants\nwill receive consideration for employment without regard to\nunlawful consideration of race, color, religion, creed,\nnational or ethnic origin, ancestry, place of birth,\ncitizenship, sex, pregnancy / childbirth or related medical\nconditions, sexual orientation, gender identity or\nexpression, marital or domestic partnership status, age,\nveteran or military status, physical or mental disability,\nmedical condition, genetic information, political /\norganizational affiliation, status as a victim or family\nmember of a victim of crime or abuse, or any other status\nprotected by applicable law.\n\nWe use artificial intelligence in our hiring process. Learn\nmore here.\n",
  "skills_required": [
    "artificial intelligence",
    "feature engineering",
    "machine learning",
    "model building"
  ],
  "skills_optional": [],
  "responsibilities": [
    "Provide technical expertise to manage end-to-end data lifecycle and deliver reliable and timely data through next-generation technologies and architecture",
    "Deliver architecture expertise across data engineering, analytics and ML, and data governance including MLOps and feature engineering",
    "Drive proof-of-concept technology development initiatives to guide new technology investments and design decisions for data lifecycle management",
    "Serve as a visible technology thought leader articulating Equinix's technology vision, strategy and architecture"
  ],
  "use_cases": [
    "Data lifecycle management and data-as-a-service architectures",
    "Data infrastructure including data lakes, data stores, and data processing engines",
    "ML and analytics platforms with MLOps, model building, and feature engineering",
    "Data governance as a service including data catalogs, discovery, lineage, and master data management"
  ],
  "tools_mentioned": [
    "DevOps",
    "MLOps",
    "cloud-native computing",
    "data catalogs",
    "data engineering",
    "data governance",
    "data infrastructure architecture",
    "data lakes",
    "data lineage",
    "data processing engines",
    "data stores",
    "data-as-a-service",
    "distributed systems",
    "master data management",
    "search"
  ],
  "frameworks_mentioned": [
    "artificial intelligence",
    "feature engineering",
    "machine learning",
    "model building"
  ],
  "languages_programming": [],
  "domains_iaml": [
    "CLOUD_DATA",
    "GENERATIVE_AI",
    "MLOPS"
  ],
  "job_family": "AI_ENGINEER",
  "ai_classification": "ai-support",
  "ai_classification_reasoning": "This is a Distinguished Engineer role focused on technology\narchitecture and strategy for data lifecycle management, ML\ninfrastructure, and AI platforms. The responsibilities\nemphasize data infrastructure, MLOps, data governance, and\narchitecture rather than hands-on model building, training,\nfine-tuning, or deploying AI models directly, which aligns\nwith ai-support classification.",
  "is_customer_facing": false,
  "is_management": false,
  "skills_categorized": {
    "genai": [
      "artificial intelligence"
    ],
    "ml": [
      "model building",
      "feature engineering",
      "machine learning"
    ],
    "web": [],
    "databases": [
      "data stores"
    ],
    "data": [
      "data engineering",
      "data lakes",
      "data processing engines",
      "search",
      "data governance",
      "data catalogs",
      "data lineage",
      "master data management",
      "distributed systems",
      "data infrastructure architecture",
      "data-as-a-service"
    ],
    "cloud": [
      "cloud-native computing"
    ],
    "ops": [
      "MLOps",
      "DevOps"
    ],
    "languages": [],
    "domains": [],
    "other": []
  },
  "scraped_at": "2026-05-15T15:38:37+00:00",
  "scraper": "skillnav-import-upstream-v1.0",
  "extraction_method": "skillnav_internal_pipeline_v1",
  "rgpd_compliant": true,
  "personal_data_stripped": true,
  "extraction_confidence": 0.9
}