{
  "job_id": "intl-ai-corpus-0791",
  "source": "intl-ai-corpus",
  "source_ref": "7034922",
  "source_url": "https://builtin.com/job/senior-software-engineer-ai-startup/7034922",
  "title": "Senior Software Engineer for AI Startup",
  "title_normalized": "AI_ENGINEER",
  "company": "Makai Labs",
  "company_type": "entité morale privée",
  "location": "INTL",
  "city_inferred": null,
  "country": "INTL",
  "remote_policy": "remote",
  "posted_date": "2026-02-04",
  "publication_month": "2026-02",
  "contract_type": "CDI",
  "work_type_raw": "FULL_TIME",
  "experience_level_text": "Expert/Leader",
  "experience_min_years": null,
  "experience_max_years": null,
  "salary_range": null,
  "company_size_raw": "14 Employees",
  "company_stage": null,
  "company_focus": "Enterprise automation platform using AI and data with human-\nmachine teaming",
  "industries": [
    "Artificial Intelligence",
    "Software",
    "Automation"
  ],
  "description": "About Makai\n\nMakai uses best-in-class Al and data to solve real-world\noperational and strategic challenges at scale. Our Makai\nAutomation Platform consists of a library of pre-built\ncomponents and modules to facilitate enterprise automation\nvia a unified human-machine teaming interface. Until now,\npeople have had to learn and adapt to software. Makai\ncreates solutions that adapt to people because technology\nwill never be 100% accurate. People are essential for all of\nour human-machine teaming solutions, as they serve as the\nfinal firewall for accuracy and quality.\n\nAbout the role\n\nThis is a full-time remote role for a Senior Software\nEngineer at Makai Labs. The Senior Software Engineer will be\nresponsible for backend app development. They will\ncollaborate with cross-functional teams to design and\nimplement innovative solutions that enhance user experiences\nand drive business outcomes.\n\nQualifications:\n\n- ﻿﻿You will support the initial discovery process to\n  understand how our clients do their work currently,\n  capturing interview notes and parsing through their\n  existing documentation, as well as documenting their\n  present-day workflows and any associated files and data\n  into comprehensive process diagrams.\n- ﻿﻿7+ years of experience in Python, with at least 4 years\n  using Flask\n- ﻿﻿Relevant experience using SQLAlchemy and pydantic.\n- ﻿﻿Relevant experience with using Docker.\n- ﻿﻿Understanding of microservices architecture and related\n  patterns\n- ﻿﻿Solid software engineering skills, with the ability to\n  produce well-structured, maintainable code\n- ﻿﻿Familiarity with modern authorization mechanisms.\n- ﻿﻿Solid experience working from a fully remote position.\n- ﻿﻿Good English communication skills.\n\nResponsibilities:\n\n- ﻿﻿Develop new features using Flask.\n- ﻿﻿Optimize applications for maximum speed and scalability.\n- ﻿﻿Ensure the technical feasibility of Ul/UX designs.\n- ﻿﻿Collaborate with frontend developers and web designers to\n  improve usability.\n- ﻿﻿Write robust, clean, and documented code.\n- ﻿﻿Maintain and enhance existing apps applications.\n- Conduct performance tests and ensure responsiveness and\n  stability across all platforms.\n\nCore values for Makai employees\n\n- ﻿﻿Have a strong work ethic. As a member of a fully remote\n  team, it is very important that you can self-manage and\n  drive your own work towards consistent excellence in a\n  timely manner.\n- Be self-sufficient and self-driven with an ownership\n  mentality, no matter your role\n- Be a flexible thinker\n- ﻿﻿Be congenial and a team player\n- ﻿﻿Always be of service to each other and our clients,\n  partners, and neighbors\n\nEmployment Type Full Time\n\n- Fully remote role\n\nBenefits\n\n- Fully remote role, Eastern time zone\n- Opportunities to work in-person with local colleagues\n- Generous PTO\n- Full health insurance premium reimbursement\n- 401(k) matching\n- Career growth & development opportunities\n",
  "skills_required": [],
  "skills_optional": [],
  "responsibilities": [
    "Develop new features using Flask for backend applications",
    "Optimize applications for maximum speed and scalability",
    "Ensure the technical feasibility of UI/UX designs",
    "Collaborate with frontend developers and web designers to improve usability",
    "Write robust, clean, and documented code",
    "Maintain and enhance existing applications",
    "Conduct performance tests and ensure responsiveness and stability across all platforms"
  ],
  "use_cases": [
    "Enterprise automation through pre-built components and modules",
    "Human-machine teaming interface for operational and strategic challenges",
    "Workflow documentation and process diagramming from client discovery",
    "Client workflow analysis and process mapping",
    "Solutions that adapt to people rather than requiring people to adapt to software"
  ],
  "tools_mentioned": [
    "Docker",
    "Flask",
    "SQLAlchemy",
    "authorization mechanisms",
    "microservices architecture",
    "pydantic"
  ],
  "frameworks_mentioned": [],
  "languages_programming": [
    "Python"
  ],
  "domains_iaml": [
    "MLOPS"
  ],
  "job_family": "AI_ENGINEER",
  "ai_classification": "ai-support",
  "ai_classification_reasoning": "This is a backend software engineer role at an AI company\nthat focuses on Flask, Python, and microservices\narchitecture. The role involves building general software\ninfrastructure and applications, not directly building,\ntraining, fine-tuning, or deploying AI models. While\nsupporting client discovery processes, the work is enabling\ntechnology for an AI product rather than hands-on AI/ML\ndevelopment.",
  "is_customer_facing": true,
  "is_management": false,
  "skills_categorized": {
    "genai": [],
    "ml": [],
    "web": [
      "Flask",
      "microservices architecture",
      "authorization mechanisms"
    ],
    "databases": [
      "SQLAlchemy"
    ],
    "data": [
      "pydantic"
    ],
    "cloud": [],
    "ops": [
      "Docker"
    ],
    "languages": [
      "Python"
    ],
    "domains": [],
    "other": []
  },
  "scraped_at": "2026-05-15T15:38:43+00:00",
  "scraper": "skillnav-import-upstream-v1.0",
  "extraction_method": "skillnav_internal_pipeline_v1",
  "rgpd_compliant": true,
  "personal_data_stripped": true,
  "extraction_confidence": 0.9
}