{
  "job_id": "intl-ai-corpus-1705",
  "source": "intl-ai-corpus",
  "source_ref": "8582806",
  "source_url": "https://builtin.com/job/software-engineer-ai-workbench/8582806",
  "title": "Software Engineer - AI Workbench",
  "title_normalized": "AI_ENGINEER",
  "company": "PhysicsX",
  "company_type": "entité morale privée",
  "location": "London, GBR",
  "city_inferred": "London",
  "country": "GB",
  "remote_policy": "hybrid",
  "posted_date": "2026-02-25",
  "publication_month": "2026-02",
  "contract_type": "CDI",
  "work_type_raw": "FULL_TIME",
  "experience_level_text": "Senior level",
  "experience_min_years": null,
  "experience_max_years": null,
  "salary_range": null,
  "company_size_raw": "67 Employees",
  "company_stage": null,
  "company_focus": "AI-driven simulation software for engineering and\nmanufacturing",
  "industries": [
    "Machine Learning",
    "Software"
  ],
  "description": "About us\n\nPhysicsX is a deep-tech company with roots in numerical\nphysics and Formula One, dedicated to accelerating hardware\ninnovation at the speed of software.\n\nWe are building an AI-driven simulation software stack for\nengineering and manufacturing across advanced industries. By\nenabling high-fidelity, multi-physics simulation through AI\ninference across the entire engineering lifecycle, PhysicsX\nunlocks new levels of optimization and automation in design,\nmanufacturing, and operations — empowering engineers to push\nthe boundaries of possibility. Our customers include leading\ninnovators in Aerospace & Defense, Materials, Energy,\nSemiconductors, and Automotive.\n\nThe Role\n\nPhysicsX is developing a platform used by Data Scientists\nand Simulation Engineers to build, train, and deploy Deep\nPhysics Models. The core of this platform relies on handling\nmassive volumes of complex simulation data, enabling high-\nfidelity multi-physics simulation through AI inference.\n\nWe are looking for a Software Engineer with a strong\nbackground in building data platforms to join our team. You\nwill not just be moving data from A to B; you will be\narchitecting and building the distributed systems, services,\nand APIs that form the backbone of our data strategy. You\nwill bridge the gap between complex physical simulations and\nmodern data infrastructure, implementing storage solutions\nfor AI/ML pipelines and creating the analytical layers that\nallow our engineers to visualise and understand their\nresults.\n\nYou will also play a key role in shaping technical direction\n— contributing to Technical Decision Records, collaborating\nwith experienced engineers, and helping to drive the\nstandards that keep our platform reliable, secure, and\nperformant. This is a role for a builder who loves coding\nrobust software as much as they love designing efficient\ndata architectures.\n\nWhat you will do\n\n- Contribute to the design and build scalable microservices,\n  APIs, and data pipelines for high-dimensional simulation\n  data across the ML lifecycle, working within established\n  architectural patterns.\n- Build and maintain automated data ingestion and processing\n  pipelines that power active learning loops, serving both\n  no-code and pro-code users.\n- Implement and integrate data infrastructure components (Data\n  Warehouses, Data Lakes, storage solutions) for simulation\n  and deep learning workloads.\n- Build internal tools that enable BI dashboards and\n  scientific data visualizations, making large datasets\n  intuitive and accessible.\n- Own features end-to-end — from implementation through\n  testing, deployment, and maintenance — writing clean,\n  well-tested, secure code.\n- Contribute to reliability standards, performance monitoring,\n  and quality of service metrics. Identify and help resolve\n  performance bottlenecks.\n- Follow and contribute to API schema standards, security\n  practices, and data access control patterns.\n- Participate in CI/CD pipeline maintenance, automated\n  testing, and observability practices, including supporting\n  zero-downtime deployments.\n- Participate in code reviews, knowledge sharing, and cross-\n  functional collaboration with data scientists and\n  researchers.\n- Contribute to Technical Decision Records and team\n  discussions on tooling and architectural trade-offs.\n\nWhat you bring to the table\n\n- A passion for the craft — you're driven by engineering\n  excellence and committed to fostering that culture across\n  the team.\n- Strong software engineering foundations — solid grasp of\n  algorithms, data structures, and system design. You write\n  clean, maintainable, testable code in Python with working\n  knowledge of Golang or Rust.\n- Data platform exposure — experience building or contributing\n  to data processing systems in production. Familiarity with\n  tools like Databricks, Snowflake, or BigQuery and concepts\n  around Data Warehouses and Data Lakes.\n- API and service design — experience working with multi-\n  service architectures, understanding schema design and\n  data access patterns.\n- Security and reliability awareness — understanding of\n  security fundamentals, monitoring, alerting, and quality\n  of service in production systems.\n- CI/CD familiarity — practical experience with CI/CD\n  pipelines and deployment workflows.\n- Safe code execution awareness — understanding of or interest\n  in sandboxing, isolation, and security considerations for\n  running user-submitted code.\n- Problem-solving — ability to diagnose issues, debug across\n  services, and optimize data processing performance.\n- Communication and collaboration — strong communication\n  skills for working with cross-functional teams.\n  Comfortable participating in code reviews and supporting\n  peers.\n- Incremental mindset — you work in small steps, balance\n  detail with the big picture, and proactively seek help\n  when blocked.\n\nIdeally\n\n- Programming skills: strong Python expertise and experience\n  with at least one compiled language (Golang, C++, or\n  Rust).\n- Data systems experience: practical experience building and\n  maintaining data processing systems, working with diverse\n  data types and running analytics on large datasets.\n- Kubernetes and infrastructure: familiarity with Kubernetes\n  concepts and infrastructure configuration tools (e.g.,\n  Helm, ArgoCD).\n- Testing and debugging: solid debugging and troubleshooting\n  skills, with exposure to automated testing practices.\n- Bonus: understanding of 3D geometry processing, physics\n  simulation data structures, or building software for\n  different deployment environments (cloud, on-premises).\n\nWhat We Offer\n\n- Equity options – share in our success and growth.\n- 10% employer pension contribution – invest in your future.\n- Free office lunches – great food to fuel your workdays.\n- Flexible working – balance your work and life in a way that\n  works for you.\n- Hybrid setup – enjoy our new Shoreditch office while keeping\n  remote flexibility.\n- Enhanced parental leave – support for life’s biggest\n  milestones.\n- Private healthcare – comprehensive coverage.\n- Personal development – access learning and training to help\n  you grow.\n- Work from anywhere – extend your remote setup to enjoy the\n  sun or reconnect with loved ones.\n\n\n\nWe value diversity and are committed to equal employment\nopportunity regardless of sex, race, religion, ethnicity,\nnationality, disability, age, sexual orientation or gender\nidentity. We strongly encourage individuals from groups\ntraditionally underrepresented in tech to apply. To help\nmake a change, we sponsor bright women from disadvantaged\nbackgrounds through their university degrees in science and\nmathematics.\n\n\n\nWe collect diversity and inclusion data solely for the\npurpose of monitoring the effectiveness of our equal\nopportunities policies and ensuring compliance with UK\nemployment and equality legislation. This information is\nconfidential, used only in aggregate form, and will not\ninfluence the outcome of your application.\n",
  "skills_required": [
    "microservices",
    "sandboxing",
    "security",
    "system design"
  ],
  "skills_optional": [],
  "responsibilities": [
    "Design and build scalable microservices, APIs, and data pipelines for high-dimensional simulation data across the ML lifecycle",
    "Build and maintain automated data ingestion and processing pipelines that power active learning loops",
    "Implement and integrate data infrastructure components including Data Warehouses, Data Lakes, and storage solutions for simulation and deep learning workloads",
    "Build internal tools that enable BI dashboards and scientific data visualizations",
    "Own features end-to-end from implementation through testing, deployment, and maintenance",
    "Contribute to reliability standards, performance monitoring, and quality of service metrics",
    "Participate in CI/CD pipeline maintenance, automated testing, and observability practices",
    "Contribute to Technical Decision Records and team discussions on tooling and architectural trade-offs"
  ],
  "use_cases": [
    "High-fidelity multi-physics simulation through AI inference",
    "Engineering and manufacturing optimization and automation",
    "Deep Physics Models for aerospace, defense, materials, energy, semiconductors, and automotive",
    "Active learning loops for continuous model improvement",
    "Scientific data visualization for complex simulation results",
    "Large-scale simulation data storage and analytics"
  ],
  "tools_mentioned": [
    "API design",
    "ArgoCD",
    "BigQuery",
    "CI/CD",
    "Data Lakes",
    "Data Warehouses",
    "Databricks",
    "Docker",
    "ETL",
    "FastAPI",
    "Helm",
    "Kubernetes",
    "REST",
    "Snowflake",
    "data pipelines",
    "monitoring",
    "observability"
  ],
  "frameworks_mentioned": [],
  "languages_programming": [
    "C++",
    "Golang",
    "Python",
    "Rust"
  ],
  "domains_iaml": [
    "DATA_ENGINEERING",
    "DEEP_LEARNING",
    "MLOPS"
  ],
  "job_family": "AI_ENGINEER",
  "ai_classification": "ai-support",
  "ai_classification_reasoning": "This role focuses on building data platforms, microservices,\nAPIs, and data pipelines that support the ML lifecycle, not\nbuilding or training the AI models themselves. The engineer\nis architecting the infrastructure and data strategy that\nenables data scientists to work with Deep Physics Models,\nwhich makes this a supporting role rather than hands-on\nAI/ML development.",
  "is_customer_facing": false,
  "is_management": false,
  "skills_categorized": {
    "genai": [],
    "ml": [],
    "web": [
      "FastAPI",
      "REST",
      "API design"
    ],
    "databases": [
      "Snowflake",
      "BigQuery",
      "Data Warehouses"
    ],
    "data": [
      "Databricks",
      "Data Lakes",
      "ETL",
      "data pipelines"
    ],
    "cloud": [],
    "ops": [
      "Kubernetes",
      "Docker",
      "CI/CD",
      "Helm",
      "ArgoCD",
      "monitoring",
      "observability"
    ],
    "languages": [
      "Python",
      "Golang",
      "Rust",
      "C++"
    ],
    "domains": [
      "3D geometry processing"
    ],
    "other": [
      "system design",
      "microservices",
      "security",
      "sandboxing"
    ]
  },
  "scraped_at": "2026-05-15T15:38:51+00:00",
  "scraper": "skillnav-import-upstream-v1.0",
  "extraction_method": "skillnav_internal_pipeline_v1",
  "rgpd_compliant": true,
  "personal_data_stripped": true,
  "extraction_confidence": 0.9
}