{
  "job_id": "intl-ai-corpus-2085",
  "source": "intl-ai-corpus",
  "source_ref": "8742088",
  "source_url": "https://builtin.com/job/senior-fullstack-engineer-support-and-ai-f-m-d/8742088",
  "title": "Senior Fullstack Engineer - Support and AI (F/M/D)",
  "title_normalized": "AI_ENGINEER",
  "company": "FREENOW",
  "company_type": "entité morale privée",
  "location": "Berlin, DEU",
  "city_inferred": "Berlin",
  "country": "DE",
  "remote_policy": "unknown",
  "posted_date": "2026-03-13",
  "publication_month": "2026-03",
  "contract_type": "CDI",
  "work_type_raw": "FULL_TIME",
  "experience_level_text": "Expert/Leader",
  "experience_min_years": null,
  "experience_max_years": null,
  "salary_range": null,
  "company_size_raw": "1,824 Employees",
  "company_stage": "Acquired (by Lyft as of July 2025)",
  "company_focus": "European multi-mobility platform offering taxis, ride-\nsharing, carsharing, e-scooters, and public transport",
  "industries": [
    "Automotive",
    "Software"
  ],
  "description": "Location: Come and join us in Berlin!\n\nJoin us as a Senior Fullstack Engineer to build the\nintuitive interfaces that power our support teams, drivers\nand passengers. You will drive the development of reliable\nand scalable solutions that power our AI assist features\nend-to-end.\n\nBe ready to join a multinational, diverse, highly motivated\nand collaborative team who strives for excellence and likes\nto have fun, while building great features and products.\n\nYOUR DAILY ADVENTURES WILL INCLUDE:\n\n- Architect, build, and maintain robust backend services.\n- Craft intuitive, powerful web applications for both end-\n  users and internal teams.\n- Interest or experience with building AI assist features\n- Own features end-to-end—from concept through to deployment\n  and performance monitoring.\n- Partner with engineers, designers, product managers, and\n  support teams to deliver meaningful, user-centered\n  solutions.\n- Experiment with AI-enhanced tools and features to elevate\n  our products and engineering practices.\n- Bring your ideas to life and help shape how we work, grow,\n  and innovate as a team.\n- Ensure systems are observable, scalable, and rock-solid\n  through modern DevOps practices.\n- Actively engage in our engineering communities—frontend and\n  backend—to share insights and stay ahead of the curve.\n- Contribute to a culture built on transparency, continuous\n  learning, and mutual respect.\n- Share your knowledge with and mentor other engineers\n\nOur Techstack: Kotlin | TypeScript | Spring | React | AWS |\nDocker | Git | Kafka & more\n\nTO BE SUCCESSFUL IN THIS ROLE:\n\n- Strong experience in backend and/or frontend development.\n- Hands-on with—or ready to dive into—Kotlin, Spring,\n  TypeScript, and React.\n- A true owner mentality—you care deeply about quality and\n  continuous improvement.\n- You thrive in a self-organized, agile team that values\n  autonomy and open communication.\n- You’re curious, and excited to learn from both deeply\n  technical and product-savvy teammates.\n- Purpose drives you—you want to do work that matters and grow\n  in an environment that supports you.\n- You bring creativity and a problem-solving mindset to\n  technical challenges.\n- You have experience in technical mentorship\n- You have interest or experience in building AI agents\n- You communicate clearly and confidently in English, both\n  written and spoken\n\nBENEFITS & PERKS IN A NUTSHELL:\n\n- Flexible working arrangements\n\n- LinkedIn Learning\n\n- Sabbatical & special leave policies\n\n- WeRoad partnership\n\n- Birthday, 24th + 31st December off\n\n- Short term EU work policy\n\n- Mobility Credit\n\n- Health Insurance\n\n- Employee assistance program\n\n DIVERSITY, EQUITY & INCLUSION:\n\nFreenow is an equal opportunity employer and we consider\nqualified applicants regardless of race, religion, national\norigin, gender, gender identity, sexual orientation,\ndisability or age. We want you to grow and evolve, bring\nyour true self to work.\n\nABOUT FREENOW:\n\nWe are Freenow, the European taxi app with the broadest\nmulti-mobility offering, available in 9 markets and over 180\ncities. Our app gives millions of passengers the freedom to\nmove with a wide choice of services including taxis, private\nhire vehicles, carsharing, car rental, e-scooters, e-bikes,\ne-mopeds and public transport.Headquartered in Hamburg and\nled by our CEO Thomas Zimmermann, we are on a mission to\nmake urban mobility more efficient, sustainable and\ninclusive.Since July 2025 we have been part of Lyft, a\nglobal mobility platform connecting riders and drivers for\nbillions of rides across North America and Europe. Together\nwe are building a more caring and connected world, creating\nnew opportunities for innovation, growth and impact.\n",
  "skills_required": [
    "AI agents",
    "AI assist features"
  ],
  "skills_optional": [],
  "responsibilities": [
    "Architect, build, and maintain robust backend services",
    "Craft intuitive, powerful web applications for end-users and internal teams",
    "Build and own AI assist features end-to-end from concept through deployment and monitoring",
    "Partner with engineers, designers, product managers, and support teams to deliver user-centered solutions",
    "Experiment with AI-enhanced tools and features to elevate products and engineering practices",
    "Ensure systems are observable, scalable, and reliable through modern DevOps practices",
    "Share knowledge and mentor other engineers",
    "Contribute to engineering communities and stay ahead of the curve"
  ],
  "use_cases": [
    "AI-powered support assistance for customer service teams",
    "Driver and passenger-facing intelligent features",
    "Internal tools enhanced with AI capabilities",
    "Mobility platform optimization",
    "Automated assistance for urban transportation"
  ],
  "tools_mentioned": [
    "AWS",
    "Docker",
    "Git",
    "Kafka",
    "React",
    "Spring"
  ],
  "frameworks_mentioned": [
    "AI agents",
    "AI assist features"
  ],
  "languages_programming": [
    "Kotlin",
    "TypeScript"
  ],
  "domains_iaml": [
    "CLOUD_DATA",
    "DATA_ENGINEERING",
    "GENERATIVE_AI",
    "MLOPS"
  ],
  "job_family": "AI_ENGINEER",
  "ai_classification": "ai-first",
  "ai_classification_reasoning": "The role explicitly involves building and owning \"AI assist\nfeatures end-to-end\" and requires interest/experience in\n\"building AI agents.\" While it's a fullstack role, the AI\ncomponent is a core responsibility, not just supporting\ninfrastructure for others' AI work.",
  "is_customer_facing": true,
  "is_management": false,
  "skills_categorized": {
    "genai": [
      "AI agents",
      "AI assist features"
    ],
    "ml": [],
    "web": [
      "Spring",
      "React"
    ],
    "databases": [],
    "data": [
      "Kafka"
    ],
    "cloud": [
      "AWS"
    ],
    "ops": [
      "Docker",
      "Git"
    ],
    "languages": [
      "Kotlin",
      "TypeScript"
    ],
    "domains": [],
    "other": []
  },
  "scraped_at": "2026-05-15T15:38:54+00:00",
  "scraper": "skillnav-import-upstream-v1.0",
  "extraction_method": "skillnav_internal_pipeline_v1",
  "rgpd_compliant": true,
  "personal_data_stripped": true,
  "extraction_confidence": 0.9
}