{
  "job_id": "linkedin-ma-2026-140",
  "source": "linkedin-ma",
  "source_url": "https://ma.linkedin.com/jobs/view/manager-data-scientist-casablanca-at-artefact-3928981813",
  "source_ref": "3928981813",
  "title": "Manager Data Scientist - Casablanca",
  "title_normalized": "DATA_SCIENTIST",
  "company": "Artefact",
  "company_id": "artefact-global",
  "company_url": "https://fr.linkedin.com/company/artefact-global",
  "company_logo": "https://media.licdn.com/dms/image/v2/D4E0BAQH6_mc4Zb_tjg/company-logo_100_100/company-logo_100_100/0/1719815465190/artefact_global_logo?e=2147483647&v=beta&t=zB-sRByAQzLDeMr12julqcZoyUFdjk8goMW6PUhUWhI",
  "company_type": "entité morale privée",
  "location": "Région كازابلانكا Métropolitaine",
  "country": "MA",
  "remote_policy": "on-site",
  "posted_date": "2026-05-01",
  "posted_date_relative_original": "قبل ‏‏٢‏ أسبوع‏",
  "deadline_date": null,
  "contract_type": null,
  "experience_level_text": null,
  "experience_min_years": null,
  "experience_max_years": null,
  "salary_range": null,
  "applications_count": "٤٦ من المتقدمين",
  "sector": null,
  "apply_type": "Easy Apply",
  "description": "Who We AreArtefact is a new generation of a data service provider, specialising in data consulting and data-driven digital marketing, dedicated to transforming data into business impact across the entire value chain of organisations. We are proud to say we’re enjoying skyrocketing growth.Our broad range of data-driven solutions in data consulting and digital marketing are designed to meet our clients’ specific needs, always conceived with a business-centric approach and delivered with tangible results. Our data-driven services are built upon the deep AI expertise we’ve acquired with our 1000+ client base around the globe.We have 850 employees across 20 offices who are focused on accelerating digital transformation. Thanks to a unique mix of company assets: State of the art data technologies, lean AI agile methodologies for fast delivery, and cohesive teams of the finest business consultants, data analysts, data scientists, data engineers, and digital experts, all dedicated to bringing extra value to every client.What You Will Be DoingAs a Manager Data Scientist, your role will encompass:Leading and conducting ambitious projects in the transformation of clients through dataDeveloping data science products and solutions for clients as well as for our data science teamWorking closely with your Consulting counterpart to build and maintain strong relationships with your clients and best understand their needsHaving a contributor role in upskilling our data science team and promoting our work within the other data departmentsCaring for the happiness of the team, ensuring that missions are delivered to a high standard and providing feedback and mentoring to less experienced Data ScientistsWriting highly optimised code to advance Artefact’s internal tool box and knowledgeWhat You Will Learn With UsDeliver impactful and successful projects on real-world problems across a variety of industries by delivering end-to-end machine learning pipelinesBuild complex solutions in feature teams with the help of your other data scientists but also ML Engineers, Data Engineers, Software Engineers and Product OwnersImprove your software engineering skills by applying ML Ops best practises and working with the Machine Learning teamsBecome an expert in one of our data science practises: Time Series Forecasting, MLOPs, NLP, Computer Vision, Optimization or Customer IntelligenceDiscover state of the art algorithms and test them during your client projects, on real world dataWhat We Are Looking ForA Doer: you get things done and inspire your teams to do the sameAn Analyst: you LOVE data and think every company should take their decisions with factsA Pragmatist: you have a hacker mindset and always find the quick winsA Mentor: your clients and teams naturally seek for your adviceAn Adventurer: you’re an entrepreneur constantly looking for problems to solveQualifications: Education & experience requiredA Master’s degree in machine learning, mathematics, computer science, or related fields3+ years of hands-on experience developing and applying data-driven solutions in a corporate or consulting setting Strong experience and knowledge of data processing, data modelling, algorithms, and data architectureFluent in at least one of the following languages: Python, R, SQL, etc…Experience in leading a technical project in a business contextIntellectual curiosity and excellent problem-solving skills, including the ability to structure and prioritise an approach for maximum impactWhy you should join usArtefact is the place to be: we train the data leaders of tomorrowInnovation: every day offers new challenges and new opportunities to learnCulture: join the best team you could ever imagineEntrepreneurship: you will be joining a team of driven entrepreneurs. We won’t give up until we make a huge dent in this industry!Still hesitating, check our medium blog to discover concrete projects!",
  "skills_required": [
    "Python",
    "SQL",
    "R",
    "Machine Learning",
    "NLP",
    "Computer Vision",
    "MLOps"
  ],
  "skills_optional": [],
  "responsibilities": [],
  "tools_mentioned": [],
  "frameworks_mentioned": [],
  "languages_programming": [
    "Python",
    "SQL",
    "R"
  ],
  "domains_iaml": [],
  "job_family": "DATA_SCIENTIST",
  "search_keyword": "Data Scientist",
  "scraped_at": "2026-05-14T23:17:00Z",
  "scraper": "skillnav-apify-number_one_scraper-v1.0",
  "rgpd_compliant": true,
  "personal_data_stripped": true,
  "extraction_confidence": 0.92,
  "extraction_method": "apify_number_one_scraper_cheap_advance_linkedin"
}